Metadata-Version: 2.1
Name: prodos
Version: 0.0.1
Summary: Lightweight glob extensions with extended path joining.
Home-page: https://github.com/beasteers/prodos
Author: Bea Steers
Author-email: bea.steers@gmail.com
License: MIT License
Keywords: glob product os.path.join join file sort make
Platform: UNKNOWN
